optimizacionpaquete_meliyork_1/__init__.py
optimizacionpaquete_meliyork_1/funcionesPrueba/__init__.py
optimizacionpaquete_meliyork_1/funcionesPrueba/funcionesMultivariables.py
optimizacionpaquete_meliyork_1/funcionesPrueba/funcionesUnivariables.py
optimizacionpaquete_meliyork_1/metodosMultivariables/__init__.py
optimizacionpaquete_meliyork_1/metodosMultivariables/caminataAleatoria.py
optimizacionpaquete_meliyork_1/metodosMultivariables/cauchy.py
optimizacionpaquete_meliyork_1/metodosMultivariables/fletcherReeves.py
optimizacionpaquete_meliyork_1/metodosMultivariables/hookeJeeves.py
optimizacionpaquete_meliyork_1/metodosMultivariables/nelderMeadSimplex.py
optimizacionpaquete_meliyork_1/metodosMultivariables/newton.py
optimizacionpaquete_meliyork_1/metodosUnivariables/__init__.py
optimizacionpaquete_meliyork_1/metodosUnivariables/biseccion.py
optimizacionpaquete_meliyork_1/metodosUnivariables/busquedaDorada.py
optimizacionpaquete_meliyork_1/metodosUnivariables/fibonacci.py
optimizacionpaquete_meliyork_1/metodosUnivariables/intervalHalving.py
optimizacionpaquete_meliyork_1/metodosUnivariables/newtonRaphson.py
optimizacionpaquete_meliyork_1/metodosUnivariables/secante.py
optimizacionpaquete_meliyork_1-0.1.dist-info/LICENSE
optimizacionpaquete_meliyork_1-0.1.dist-info/METADATA
optimizacionpaquete_meliyork_1-0.1.dist-info/WHEEL
optimizacionpaquete_meliyork_1-0.1.dist-info/top_level.txt
optimizacionpaquete_meliyork_1-0.1.dist-info/RECORD
